<PAMDataset>
  <Metadata>
    <MDI key="DataType">Generic</MDI>
  </Metadata>
  <Metadata domain="Esri">
    <MDI key="PyramidResamplingType">NEAREST</MDI>
  </Metadata>
  <PAMRasterBand band="1">
    <Histograms>
      <HistItem>
        <HistMin>-0.5</HistMin>
        <HistMax>230.5</HistMax>
        <BucketCount>231</BucketCount>
        <IncludeOutOfRange>1</IncludeOutOfRange>
        <Approximate>0</Approximate>
        <HistCounts>7783|70|53|72|284|109|35|12310|14|24|44|16|56|58|51|35|1121|114|494|83|117|29|396|108|46|275|26|29|29|82|1377|101|68|701|338|7|955|104|637|37|21|29|163|10|18|27|11|49|44|46|997|14|39|113|533|67|12|318|42|39|53|1550|141|101|25|9|1008|50|45|1341|43|68|532|24|44|124|87|117|86|445|8|386|6978|374|308|296|310|442|320|1441|698|266|1675|282|285|233|1285|377|315|443|296|732|411|532|485|220|386|296|325|173|367|363|291|201|193|394675|69|61|245|884|1774|922|306|129|84|22180|107|1769|337|243|1061|111587|40|65|114|904|103|56|51|123|85|68|48|123|45|79|37|102|35|36|42|44|142|39|49|816|35|72|41|1191|57|44|102|15843|1724|1146|33|1140|36|22|1157|105|48|270|484|23|24|367|1162|53|93|31|24|698|52|29|5502|17|29|24|23|21|129|31|32|30|27|1419|179|128|85|25126|37|890|143|201|145|88|69|87|93|187|1108810|9|13|11|125|24|18|18|38|33|18|22|41|75|52|80|64|103|885</HistCounts>
      </HistItem>
    </Histograms>
    <Metadata>
      <MDI key="STATISTICS_MINIMUM">0</MDI>
      <MDI key="STATISTICS_MAXIMUM">230</MDI>
      <MDI key="STATISTICS_MEAN">177.27496988245</MDI>
      <MDI key="STATISTICS_STDDEV">49.213347127566</MDI>
      <MDI key="STATISTICS_SKIPFACTORX">1</MDI>
      <MDI key="STATISTICS_SKIPFACTORY">1</MDI>
      <MDI key="STATISTICS_EXCLUDEDVALUES"></MDI>
      <MDI key="STATISTICS_COVARIANCES">2421.95353549827,1763.81974447714,1098.90002331825</MDI>
    </Metadata>
  </PAMRasterBand>
  <PAMRasterBand band="2">
    <Histograms>
      <HistItem>
        <HistMin>-0.5</HistMin>
        <HistMax>242.5</HistMax>
        <BucketCount>243</BucketCount>
        <IncludeOutOfRange>1</IncludeOutOfRange>
        <Approximate>0</Approximate>
        <HistCounts>7731|66|44|62|72|91|245|12302|2|14|7|30|12|40|28|40|25|12|13|61|63|23|13|28|20|480|1297|6|8|19|31|705|458|1412|101|2|9|5|4|935|80|48|34|9|22|11|22|25|5|18|43|292|710|31|33|16|155|365|26|30|38|56|12|9|32|40|28|831|108|1396|38|7|931|14|42|44|71|331|61|1101|5|328|124|410|149|102|79|10|28|10|6983|121|184|258|118|575|483|131|248|124|224|91|1340|107|115|307|1136|575|170|1411|604|120|579|90|135|89|112|371|97|158|232|117|142|120|184|143|95|143|102|205|88|192|61|206|77|62|239|22265|614|490|1698|1446|730|1195|161|470|335|140|1000|92|131|306|486|359|196|602|205|706|384|720|1352|318|699|242|557|148|166|348|90|149|924|180|270|112|166|1233|172|217|111579|166|16117|1427|395653|44|1128|25030|18|22|1142|56|57|495|116|63|34|22|1201|64|65|44|21|699|9|75|48|26|255|57|17|26|25|20|5512|79|21|32|135|57|87|57|64|44|24|38|963|85|102|124|100|101|897|12|18|87|1108784|0|0|0|0|0|0|0|24</HistCounts>
      </HistItem>
    </Histograms>
    <Metadata>
      <MDI key="STATISTICS_MINIMUM">0</MDI>
      <MDI key="STATISTICS_MAXIMUM">242</MDI>
      <MDI key="STATISTICS_MEAN">209.69245795409</MDI>
      <MDI key="STATISTICS_STDDEV">39.350673185847</MDI>
      <MDI key="STATISTICS_SKIPFACTORX">1</MDI>
      <MDI key="STATISTICS_SKIPFACTORY">1</MDI>
      <MDI key="STATISTICS_EXCLUDEDVALUES"></MDI>
      <MDI key="STATISTICS_COVARIANCES">1763.81974447714,1548.47548017935,1294.32412956659</MDI>
    </Metadata>
  </PAMRasterBand>
  <PAMRasterBand band="3">
    <Histograms>
      <HistItem>
        <HistMin>-0.5</HistMin>
        <HistMax>245.5</HistMax>
        <BucketCount>246</BucketCount>
        <IncludeOutOfRange>1</IncludeOutOfRange>
        <Approximate>0</Approximate>
        <HistCounts>7783|69|45|66|66|94|40|12283|220|17|26|6|11|44|13|55|24|16|14|39|83|455|69|30|8|17|145|295|8|19|36|386|74|18|2458|201|30|8|13|7|1332|126|95|307|17|20|7|20|151|8|17|11|16|42|3|38|15|361|14|12|23|53|54|16|16|584|39|80|1520|355|64|62|14|1269|16|6|42|21|126|76|48|171|29|38|86|21|26|32|36|435|9|7|7172|109|92|175|88|86|194|164|103|140|90|39|2270|103|71|105|1442|235|279|186|189|150|82|534|273|340|62|58|91|76|25056|536|83|69|143|151|44|243|68|287|99|91|82|126|333|61|81|196|22267|103|78|2886|406|602|1662|90|159|111500|99|948|163|70|275|86|92|182|173|113|117|232|117|55|50|63|217|41|136|78|129|58|146|806|345|50|94|62|71|1640|89|149|312|16240|1756|2423|548|1194|646|135|654|1207|808|118|116|1894|468|126|125|112|1842|80|184|161|52|740|417|94|168|109|57|104|75|61|97|93|256|73|72|255|118|97|232|208|112|5627|94|199|1149|152|1030|139|122|115|64|124|37|130|1108891|394473|0|0|0|0|0|24</HistCounts>
      </HistItem>
    </Histograms>
    <Metadata>
      <MDI key="STATISTICS_MINIMUM">0</MDI>
      <MDI key="STATISTICS_MAXIMUM">245</MDI>
      <MDI key="STATISTICS_MEAN">222.73906275074</MDI>
      <MDI key="STATISTICS_STDDEV">41.790064785865</MDI>
      <MDI key="STATISTICS_SKIPFACTORX">1</MDI>
      <MDI key="STATISTICS_SKIPFACTORY">1</MDI>
      <MDI key="STATISTICS_EXCLUDEDVALUES"></MDI>
      <MDI key="STATISTICS_COVARIANCES">1098.90002331825,1294.32412956659,1746.40951480683</MDI>
    </Metadata>
  </PAMRasterBand>
</PAMDataset>
